metalsmith/__init__.py
metalsmith/_cmd.py
metalsmith/_format.py
metalsmith/_instance.py
metalsmith/_network_metadata.py
metalsmith/_nics.py
metalsmith/_provisioner.py
metalsmith/_scheduler.py
metalsmith/_utils.py
metalsmith/exceptions.py
metalsmith/instance_config.py
metalsmith/sources.py
metalsmith/version.py
metalsmith/test/__init__.py
metalsmith/test/test_cmd.py
metalsmith/test/test_instance.py
metalsmith/test/test_instance_config.py
metalsmith/test/test_metalsmith_instances.py
metalsmith/test/test_network_metadata.py
metalsmith/test/test_nics.py
metalsmith/test/test_provisioner.py
metalsmith/test/test_scheduler.py
metalsmith/test/test_sources.py
metalsmith/test/test_utils.py
metalsmith-2.5.0.data/data/share/ansible/plugins/modules/metalsmith_deployment_defaults.py
metalsmith-2.5.0.data/data/share/ansible/plugins/modules/metalsmith_instances.py
metalsmith-2.5.0.data/data/share/ansible/roles/metalsmith_deployment/README.rst
metalsmith-2.5.0.data/data/share/ansible/roles/metalsmith_deployment/defaults/main.yml
metalsmith-2.5.0.data/data/share/ansible/roles/metalsmith_deployment/meta/main.yml
metalsmith-2.5.0.data/data/share/ansible/roles/metalsmith_deployment/tasks/main.yml
metalsmith-2.5.0.dist-info/AUTHORS
metalsmith-2.5.0.dist-info/LICENSE
metalsmith-2.5.0.dist-info/METADATA
metalsmith-2.5.0.dist-info/WHEEL
metalsmith-2.5.0.dist-info/entry_points.txt
metalsmith-2.5.0.dist-info/pbr.json
metalsmith-2.5.0.dist-info/top_level.txt
metalsmith-2.5.0.dist-info/RECORD
