Metadata-Version: 2.1
Name: metalsmith
Version: 2.5.0
Summary: Deployment and Scheduling tool for Bare Metal
Home-page: https://opendev.org/openstack/metalsmith
Author: OpenStack
Author-email: openstack-discuss@lists.openstack.org
License: Apache-2
Classifier: Environment :: Console
Classifier: Environment :: OpenStack
Classifier: Intended Audience :: System Administrators
Classifier: Intended Audience :: Information Technology
Classifier: License :: OSI Approved :: Apache Software License
Classifier: Operating System :: OS Independent
Classifier: Programming Language :: Python
Classifier: Programming Language :: Python :: Implementation :: CPython
Classifier: Programming Language :: Python :: 3 :: Only
Classifier: Programming Language :: Python :: 3
Classifier: Programming Language :: Python :: 3.9
Classifier: Programming Language :: Python :: 3.10
Classifier: Programming Language :: Python :: 3.11
Classifier: Programming Language :: Python :: 3.12
Requires-Python: >=3.9
License-File: LICENSE
License-File: AUTHORS
Requires-Dist: pbr !=2.1.0,>=2.0.0
Requires-Dist: openstacksdk >=0.29.0
Requires-Dist: requests >=2.18.4
Requires-Dist: PrettyTable >=0.7.2
